[
    {
        "วันที่": "2022-09-09 07:28:39",
        "หัวเรื่อง": "Siam Paragon Bangkok International Fashion Week 2022 (BIFW2022) 21-25 กันยายน 2565 ณ สยามพารากอน - อาร์วายที9",
        "แหล่งข่าว": " อาร์วายที9",
        "ลิงค์": "https://www.ryt9.com/s/prg/3355430"
    },
    {
        "วันที่": "2022-09-08 23:00:00",
        "หัวเรื่อง": "ในประเทศ - ชุมทางอีสาน : 9 กันยายน 2565 - หนังสือพิมพ์แนวหน้า",
        "แหล่งข่าว": " ชุมทางอีสาน : 9 กันยายน 2565 - หนังสือพิมพ์แนวหน้า",
        "ลิงค์": "https://www.naewna.com/local/678875"
    },
    {
        "วันที่": "2022-09-08 15:16:24",
        "หัวเรื่อง": "ต้อนรับวิทยาการการประชุมการเข้าร่วมเครือข่ายวิจัย - เชียงไหม่นิวส์",
        "แหล่งข่าว": " เชียงไหม่นิวส์",
        "ลิงค์": "https://www.chiangmainews.co.th/social/2727385/"
    },
    {
        "วันที่": "2022-09-07 15:19:32",
        "หัวเรื่อง": "รองปลัดกระทรวงดิจิทัลฯ ร่วมงาน \"Digital Transformation 2022\" บรรยายหัวข้อ \"PDPA Basic - อาร์วายที9",
        "แหล่งข่าว": " อาร์วายที9",
        "ลิงค์": "https://www.ryt9.com/s/prg/3354722"
    },
    {
        "วันที่": "2022-09-07 04:41:42",
        "หัวเรื่อง": "เปิดกำหนดการรับสมัคร TCAS66 ม.ขอนแก่น เริ่มรอบแรก 22 พฤศจิกายนนี้ - Dek-D.COM",
        "แหล่งข่าว": " Dek-D.COM",
        "ลิงค์": "https://www.dek-d.com/tcas/61078/"
    },
    {
        "วันที่": "2022-09-07 00:35:00",
        "หัวเรื่อง": "ฝนถล่ม กทม.ท่วมหลายจุด-ม.เกษตรศาสตร์อ่วม - ผู้จัดการออนไลน์",
        "แหล่งข่าว": " ผู้จัดการออนไลน์",
        "ลิงค์": "https://mgronline.com/onlinesection/detail/9650000085779"
    },
    {
        "วันที่": "2022-09-06 10:48:00",
        "หัวเรื่อง": "จ.ขอนแก่น เตรียมจัดงาน\"อีสานอุตสาหกรรมแฟร์\" ปีที่ 7 - บ้านเมือง",
        "แหล่งข่าว": " บ้านเมือง",
        "ลิงค์": "https://www.banmuang.co.th/news/region/295127"
    },
    {
        "วันที่": "2022-09-06 01:57:00",
        "หัวเรื่อง": "คณะบริหารธุรกิจ SPU ขอนแก่น ทีม SUCCESS ผ่านเข้ารอบ 18 ทีม โครงการประชันแผนธุรกิจเสมือนจริงของ - อาร์วายที9",
        "แหล่งข่าว": " อาร์วายที9",
        "ลิงค์": "https://www.ryt9.com/s/prg/3354085"
    },
    {
        "วันที่": "2022-09-05 23:00:00",
        "หัวเรื่อง": "รายงานพิเศษ : มข.เปิดพื้นที่เชิงสร้างสรรค์ด้านภาพยนตร์ เทศกาลหนังเมืองแคน ครั้งที่ 6 (Kaen International Film Festival) - หนังสือพิมพ์แนวหน้า",
        "แหล่งข่าว": " หนังสือพิมพ์แนวหน้า",
        "ลิงค์": "https://www.naewna.com/local/678075"
    },
    {
        "วันที่": "2022-09-05 13:02:00",
        "หัวเรื่อง": "ม.ขอนแก่นปัดจ่ายเยียวยา 66 ล้าน นศ.แพทย์ถูกบัสชนดับ ยันจะจ่ายก็ต่อเมื่อศาลสั่ง - ผู้จัดการออนไลน์",
        "แหล่งข่าว": " ผู้จัดการออนไลน์",
        "ลิงค์": "https://mgronline.com/local/detail/9650000085340"
    },
    {
        "วันที่": "2022-09-05 12:22:22",
        "หัวเรื่อง": "ม.ขอนแก่น เปิดหลักสูตรแพทย์ 2 ปริญญา เรียน 6 ปี ควบตรี-โท - ประชาชาติธุรกิจ",
        "แหล่งข่าว": " ประชาชาติธุรกิจ",
        "ลิงค์": "https://www.prachachat.net/education/news-1038694"
    },
    {
        "วันที่": "2022-09-05 10:30:00",
        "หัวเรื่อง": "วช.หนุนนวัตกรรมเลเซอร์สำหรับใช้ส่งเสริมสุขภาพช่องปากผู้สูงอายุในระดับปฐมภูมิ - อาร์วายที9",
        "แหล่งข่าว": " อาร์วายที9",
        "ลิงค์": "https://www.ryt9.com/s/prg/3354551"
    },
    {
        "วันที่": "2022-09-05 04:58:08",
        "หัวเรื่อง": "จับตาปลัดเกษตรคนใหม่ วัดใจ \"เฉลิมชัย\" คาดเคาะ 3 รายชื่อ เสนอ ครม.พรุ่งนี้ - ประชาชาติธุรกิจ",
        "แหล่งข่าว": " ประชาชาติธุรกิจ",
        "ลิงค์": "https://www.prachachat.net/economy/news-1038122"
    },
    {
        "วันที่": "2022-09-05 04:03:50",
        "หัวเรื่อง": "มช.จับมือ ม.สงขลา และม.ขอนแก่น จัดโครงการประชุมวิชาการ - เชียงไหม่นิวส์",
        "แหล่งข่าว": " เชียงไหม่นิวส์",
        "ลิงค์": "https://www.chiangmainews.co.th/learning/2723231/"
    },
    {
        "วันที่": "2022-09-04 23:00:00",
        "หัวเรื่อง": "มข.-Universitat Muhamadiyah Yogyakarta เดินหน้าพัฒนาความร่วมมือด้านวิชาการ และวิจัย - หนังสือพิมพ์แนวหน้า",
        "แหล่งข่าว": " หนังสือพิมพ์แนวหน้า",
        "ลิงค์": "https://www.naewna.com/local/677787"
    },
    {
        "วันที่": "2022-09-03 12:50:00",
        "หัวเรื่อง": "เปิดเกณฑ์ TCAS66 \"คณะแพทยศาสตร์\" ม.ขอนแก่น รับกว่า 288 ที่นั่ง รวมหลักสูตรใหม่ - Dek-D.COM",
        "แหล่งข่าว": " Dek-D.COM",
        "ลิงค์": "https://www.dek-d.com/tcas/61049/"
    },
    {
        "วันที่": "2022-09-03 12:21:00",
        "หัวเรื่อง": "ไม่ขอทน \"หมา\" โดนปั่นจักรยานมายิงถึงหน้าบ้าน เจ้าของร้องตำรวจ ล่าตัวคนร้าย - คมชัดลึก",
        "แหล่งข่าว": " คมชัดลึก",
        "ลิงค์": "https://www.komchadluek.net/news/crime/528538"
    },
    {
        "วันที่": "2022-09-03 07:00:00",
        "หัวเรื่อง": "สถานการณ์แรงงานประจำสัปดาห์ 3-9 ก.ย. 2565 - Prachatai",
        "แหล่งข่าว": " Prachatai",
        "ลิงค์": "https://prachatai.com/journal/2022/09/100433"
    },
    {
        "วันที่": "2022-09-02 04:24:00",
        "หัวเรื่อง": "#dek66 เตรียมตัว! ม.ขอนแก่น เปิดหลักสูตรใหม่ \"แพทยสองปริญญา\" (ตรีควบโท) - Dek-D.COM",
        "แหล่งข่าว": " Dek-D.COM",
        "ลิงค์": "https://www.dek-d.com/tcas/60934/"
    },
    {
        "วันที่": "2022-09-02 03:07:00",
        "หัวเรื่อง": "นำร่องแล้ว! โลตัส ร่วม ม.ขอนแก่น เพิ่มมูลค่าให้อาหารที่จำหน่ายไม่หมด บริจาคให้เกษตรกรใช้เลี้ยงแมลงโปรตีน - ผู้จัดการออนไลน์",
        "แหล่งข่าว": " ผู้จัดการออนไลน์",
        "ลิงค์": "https://mgronline.com/greeninnovation/detail/9650000084280"
    },
    {
        "วันที่": "2022-09-01 04:56:14",
        "หัวเรื่อง": "ประชาชนไฟเขียวกองสลากฯ ออกผลิตภัณฑ์ใหม่ 6 หลัก-3 หลัก แก้ขายแพง/หวยเถื่อน : อินโฟเควสท์ - สำนักข่าวอินโฟเควสท์",
        "แหล่งข่าว": " สำนักข่าวอินโฟเควสท์",
        "ลิงค์": "https://www.infoquest.co.th/2022/230294"
    },
    {
        "วันที่": "2022-08-31 07:00:00",
        "หัวเรื่อง": "ประกาศผลสอบ ก.พ.65 เช็กรายชื่อผู้สอบผ่าน ก.พ.(e-Exam) ที่นี่! - TrueID News",
        "แหล่งข่าว": " TrueID News",
        "ลิงค์": "https://news.trueid.net/detail/LwGAPaooN45X"
    },
    {
        "วันที่": "2022-08-30 07:00:00",
        "หัวเรื่อง": "\"หมอทวีศิลป์\" จาก โฆษก ศบค.-ผู้ตรวจราชการฯ สู่ตำแหน่ง \"รองปลัดสาธารณสุข\" - ฐานเศรษฐกิจ",
        "แหล่งข่าว": " ฐานเศรษฐกิจ",
        "ลิงค์": "https://www.thansettakij.com/general-news/538476"
    },
    {
        "วันที่": "2022-08-30 07:00:00",
        "หัวเรื่อง": "อธิบดีกรมส่งเสริมสหกรณ์ แจกทุนเรียนฟรี ป.ตรี ทายาทสหกรณ์โคนม - ฐานเศรษฐกิจ",
        "แหล่งข่าว": " ฐานเศรษฐกิจ",
        "ลิงค์": "https://www.thansettakij.com/economy/trade/538460"
    },
    {
        "วันที่": "2022-08-30 07:00:00",
        "หัวเรื่อง": "เปิดวิสัยทัศน์ “วรวุฒิ กุลแก้ว” กับภารกิจขับเคลื่อนมูลนิธิ “ทันตนวัตกรรม” - ไทยโพสต์",
        "แหล่งข่าว": " ไทยโพสต์",
        "ลิงค์": "https://www.thaipost.net/public-relations-news/210991/"
    },
    {
        "วันที่": "2022-08-28 07:00:00",
        "หัวเรื่อง": "KKBS ม.ขอนแก่น ประกาศความสำเร็จผ่านเกณฑ์ประเมิน EdPEx300 - ผู้จัดการออนไลน์",
        "แหล่งข่าว": " ผู้จัดการออนไลน์",
        "ลิงค์": "https://mgronline.com/local/detail/9650000082481"
    },
    {
        "วันที่": "2022-08-28 07:00:00",
        "หัวเรื่อง": "มข.ผุดหลักสูตร \"แคนอคาเดมี\" ปั้นผู้ประกอบการหนังรุ่นใหม่ประดับวงการ - คมชัดลึก",
        "แหล่งข่าว": " คมชัดลึก",
        "ลิงค์": "https://www.komchadluek.net/news/education/527918"
    },
    {
        "วันที่": "2022-08-28 07:00:00",
        "หัวเรื่อง": "โลตัส ร่วมกับ ม.ขอนแก่น เพิ่มมูลค่าให้อาหารที่จำหน่ายไม่หมด - คมชัดลึก",
        "แหล่งข่าว": " คมชัดลึก",
        "ลิงค์": "https://www.komchadluek.net/news/education/527843"
    },
    {
        "วันที่": "2022-08-28 07:00:00",
        "หัวเรื่อง": "\"มข.” ช่วยเหลือครอบครัว นศ. หลังเกิดเหตุรถบัสชน จยย.นศ.ดับ - กรุงเทพธุรกิจ",
        "แหล่งข่าว": " กรุงเทพธุรกิจ",
        "ลิงค์": "https://www.bangkokbiznews.com/social/social_education/1023452"
    },
    {
        "วันที่": "2022-08-28 07:00:00",
        "หัวเรื่อง": "\"มข.\" เตรียมจัด “มหกรรมมหาวิทยาลัยขอนแก่นบริการชุมชน” 16 ก.ย. นี้ - กรุงเทพธุรกิจ",
        "แหล่งข่าว": " กรุงเทพธุรกิจ",
        "ลิงค์": "https://www.bangkokbiznews.com/social/social_education/1023416"
    },
    {
        "วันที่": "2022-08-27 07:00:00",
        "หัวเรื่อง": "\"มข.\"เผยการช่วยเหลือครอบครัว นศ. หลังเกิดอุบัติเหตุรถบัสชนจยย.นศ.ดับ - บ้านเมือง",
        "แหล่งข่าว": " บ้านเมือง",
        "ลิงค์": "https://www.banmuang.co.th/news/region/293780"
    },
    {
        "วันที่": "2022-08-25 07:00:00",
        "หัวเรื่อง": "“KGO Token-เหรียญดิจิทัลแรกเมืองไทย” อีกบทพิสูจน์ขอนแก่นสมาร์ทซิตี้ ร้านค้าร่วมรับนับพันแห่งแล้ว! - ผู้จัดการออนไลน์",
        "แหล่งข่าว": " ผู้จัดการออนไลน์",
        "ลิงค์": "https://mgronline.com/local/detail/9650000081645"
    },
    {
        "วันที่": "2022-08-25 07:00:00",
        "หัวเรื่อง": "สำนักงานสลากเพิ่มปริมาณสลากดิจิทัลงวด 1 ก.ย.นี้ เป็น 11.4 ล้านใบ - กรุงเทพธุรกิจ",
        "แหล่งข่าว": " กรุงเทพธุรกิจ",
        "ลิงค์": "https://www.bangkokbiznews.com/business/business_finance/1022995"
    },
    {
        "วันที่": "2022-08-24 07:00:00",
        "หัวเรื่อง": "ยลโฉม 15 สาวงาม ผู้เข้าประกวด Miss Earth Thailand 2022 ห้ามพลาด! “พีพีทีวี” ถ่ายทอดสด \"รอบตัดสิน\" 29 ส.ค.นี้ - PPTVHD36",
        "แหล่งข่าว": " PPTVHD36",
        "ลิงค์": "https://www.pptvhd36.com/news/%E0%B8%82%E0%B9%88%E0%B8%B2%E0%B8%A7%E0%B8%9A%E0%B8%B1%E0%B8%99%E0%B9%80%E0%B8%97%E0%B8%B4%E0%B8%87/179185"
    },
    {
        "วันที่": "2022-08-24 07:00:00",
        "หัวเรื่อง": "คปภ.ขอนแก่นลงนาม MOU ประกันภัยมะเร็งท่อน้ำดี - ผู้จัดการออนไลน์",
        "แหล่งข่าว": " ผู้จัดการออนไลน์",
        "ลิงค์": "https://mgronline.com/local/detail/9650000081302"
    },
    {
        "วันที่": "2022-08-23 07:00:00",
        "หัวเรื่อง": "ม.ขอนแก่น เปิดรับสมัคร ฝึกงานบนเรือสำราญ 1 ปี เงินเดือน 30,000 บาท - อีจัน Ejan",
        "แหล่งข่าว": " อีจัน Ejan",
        "ลิงค์": "https://www.ejan.co/ejan-market/r5948jel14"
    },
    {
        "วันที่": "2022-08-23 07:00:00",
        "หัวเรื่อง": "แม่ \"น้องอาย\" เรียกค่าเยียวยา หลังลูกสาวนศ.แพทย์ ถูกรถบัสชนดับ 66 ล้าน - Post Today",
        "แหล่งข่าว": " Post Today",
        "ลิงค์": "https://www.posttoday.com/social/general/687056"
    },
    {
        "วันที่": "2022-08-23 07:00:00",
        "หัวเรื่อง": "\"มข.-วช.\" มอบชุดคัดกรอง \"พยาธิใบไม้ตับ\" 4 หมื่นชุด ให้กรมควบคุมโรค - กรุงเทพธุรกิจ",
        "แหล่งข่าว": " กรุงเทพธุรกิจ",
        "ลิงค์": "https://www.bangkokbiznews.com/social/public_health/1022603"
    },
    {
        "วันที่": "2022-08-23 07:00:00",
        "หัวเรื่อง": "แม่ \"น้องอาย\" นศ.แพทย์ ยื่นข้อเสนอ มข. เยียวยา 66 ล้าน บัสคณะพยาบาลชนลูกดับ - Sanook",
        "แหล่งข่าว": " Sanook",
        "ลิงค์": "https://www.sanook.com/news/8611950/"
    },
    {
        "วันที่": "2022-08-23 02:21:34",
        "หัวเรื่อง": "แม่นักศึกษาแพทย์ เรียก มข.66 ล้านบาท เยียวยาลูกสาวถูกรถบัสชนเสียชีวิต - ช่อง 7HD",
        "แหล่งข่าว": " ช่อง 7HD",
        "ลิงค์": "https://news.ch7.com/detail/590062"
    },
    {
        "วันที่": "2022-08-22 07:00:00",
        "หัวเรื่อง": "พ.ร.ก. ฉุกเฉินฯ ยังใช้คุมโควิด หรือเพื่อคุมการชุมนุมสาธารณะ - บีบีซีไทย",
        "แหล่งข่าว": " บีบีซีไทย",
        "ลิงค์": "https://www.bbc.com/thai/articles/crg0ydqklkpo"
    },
    {
        "วันที่": "2022-08-22 07:00:00",
        "หัวเรื่อง": "รายงานพิเศษ : อลังการงานสร้าง วงโปงลางสินไซ มข. คว้าชัยถ้วยพระราชทาน-รางวัลอื่นๆ อีกมากมาย - หนังสือพิมพ์แนวหน้า",
        "แหล่งข่าว": " หนังสือพิมพ์แนวหน้า",
        "ลิงค์": "https://www.naewna.com/local/674801"
    },
    {
        "วันที่": "2022-08-22 07:00:00",
        "หัวเรื่อง": "มข.พร้อมจัด “มหกรรมมหาวิทยาลัยขอนแก่นบริการชุมชน” ฟรีไม่เสียค่าใช้จ่าย ! - บ้านเมือง",
        "แหล่งข่าว": " บ้านเมือง",
        "ลิงค์": "https://www.banmuang.co.th/news/region/293186"
    },
    {
        "วันที่": "2022-08-22 07:00:00",
        "หัวเรื่อง": "รีวิวเที่ยวงานมหกรรมหนังสือภาคอีสานครั้งที่ 10 ที่มหาวิทยาลัยขอนแก่น #รีวิว - TrueID Travel",
        "แหล่งข่าว": " TrueID Travel",
        "ลิงค์": "https://travel.trueid.net/detail/J2dbd04wzr6A"
    },
    {
        "วันที่": "2022-08-22 07:00:00",
        "หัวเรื่อง": "มข.เปิดรับฝึกงานบนเรือสำราญ ที่อเมริกา - เชียงไหม่นิวส์",
        "แหล่งข่าว": " เชียงไหม่นิวส์",
        "ลิงค์": "https://www.chiangmainews.co.th/topstories/2263042/"
    },
    {
        "วันที่": "2022-08-22 07:00:00",
        "หัวเรื่อง": "อ่านกลยุทธ์ \"สามก๊ก” มิติใหม่ ชีวิตก้าวหน้ายุคทันสมัย / ดร.สุวัฒน์ ทองธนากุล - ผู้จัดการออนไลน์",
        "แหล่งข่าว": " ผู้จัดการออนไลน์",
        "ลิงค์": "https://mgronline.com/goodhealth/detail/9650000080293"
    },
    {
        "วันที่": "2022-08-21 07:00:00",
        "หัวเรื่อง": "\"ขอนแก่นมาราธอนนานาชาติ ครั้งที่ 18\" เปิดรับสมัคร 24 - 26 ส.ค.นี้ - กรุงเทพธุรกิจ",
        "แหล่งข่าว": " 26 ส.ค.นี้ - กรุงเทพธุรกิจ",
        "ลิงค์": "https://www.bangkokbiznews.com/social/social_education/1022269"
    },
    {
        "วันที่": "2022-08-21 07:00:00",
        "หัวเรื่อง": "ม.ขอนแก่น รับสมัครผู้สนใจฝึกงานเรือสำราญ 1 ปี เงินเดือน 3 หมื่นบาท - ประชาชาติธุรกิจ",
        "แหล่งข่าว": " ประชาชาติธุรกิจ",
        "ลิงค์": "https://www.prachachat.net/education/news-1021811"
    },
    {
        "วันที่": "2022-08-21 07:00:00",
        "หัวเรื่อง": "ค้นหาทุกคำตอบ! สอบ \"TCAS 66 - กสพท\" แตกต่างจากเดิม เด็ก66 ต้องรู้อะไรบ้าง? - กรุงเทพธุรกิจ",
        "แหล่งข่าว": " กสพท\" แตกต่างจากเดิม เด็ก66 ต้องรู้อะไรบ้าง? - กรุงเทพธุรกิจ",
        "ลิงค์": "https://www.bangkokbiznews.com/social/social_education/1022221"
    },
    {
        "วันที่": "2022-08-19 07:00:00",
        "หัวเรื่อง": "หอการค้าขอนแก่น จัด “สมาร์ทบิซิเนส เอ็กซ์โป 2022\" ดันเงินสะพัดกว่า 500 ล. - ฐานเศรษฐกิจ",
        "แหล่งข่าว": " ฐานเศรษฐกิจ",
        "ลิงค์": "https://www.thansettakij.com/economy/industry/537243"
    },
    {
        "วันที่": "2022-08-19 07:00:00",
        "หัวเรื่อง": "I-SAN BOOK FAIR 2022 ม.ขอนแก่น คนรักการอ่านภาคอีสานคึกคัก - ประชาชาติธุรกิจ",
        "แหล่งข่าว": " ประชาชาติธุรกิจ",
        "ลิงค์": "https://www.prachachat.net/d-life/news-1014420"
    },
    {
        "วันที่": "2022-08-15 07:00:00",
        "หัวเรื่อง": "นักวิชาการชำแหละ เกมต้มเปื่อยพรรคเล็ก แคนดิเดตนายกฯเหลือแค่ 3 ชื่อ - ไทยโพสต์",
        "แหล่งข่าว": " ไทยโพสต์",
        "ลิงค์": "https://www.thaipost.net/politics-news/200997/"
    },
    {
        "วันที่": "2022-08-15 07:00:00",
        "หัวเรื่อง": "'มข.'ปลูกฝังเด็กวัยฟันน้ำนม จัดกิจกรรมดำนาปลูกข้าว - บ้านเมือง",
        "แหล่งข่าว": " บ้านเมือง",
        "ลิงค์": "https://www.banmuang.co.th/mobile/news/region/292171"
    },
    {
        "วันที่": "2022-08-14 07:00:00",
        "หัวเรื่อง": "“สมศักดิ์” เร่งวิจัย “เห็ดขี้ควาย” สกัดทำยารักษาโรคซึมเศร้า เตือนยังผิดกฎหมาย - ผู้จัดการออนไลน์",
        "แหล่งข่าว": " ผู้จัดการออนไลน์",
        "ลิงค์": "https://mgronline.com/crime/detail/9650000077616"
    },
    {
        "วันที่": "2022-08-13 07:00:00",
        "หัวเรื่อง": "รมว.พม. ทอดผ้าป่ากองบุญแห่งการให้ จ.ขอนแก่น - บ้านเมือง",
        "แหล่งข่าว": " บ้านเมือง",
        "ลิงค์": "https://www.banmuang.co.th/news/region/291930"
    },
    {
        "วันที่": "2022-08-12 07:16:06",
        "หัวเรื่อง": "เผยนาทีสลด! นศ.แพทย์ถูกรถชนดับใน ม.ขอนแก่น - ช่องวัน 31",
        "แหล่งข่าว": " ช่องวัน 31",
        "ลิงค์": "https://www.one31.net/news/detail/57079"
    },
    {
        "วันที่": "2022-08-11 07:00:00",
        "หัวเรื่อง": "อาจารย์-รุ่นพี่-เพื่อน ร่วมอาลัย-รดน้ำศพ นักศึกษาแพทย์ มข.ถูกรถบัสชนดับ - ข่าวไทยพีบีเอส",
        "แหล่งข่าว": " ข่าวไทยพีบีเอส",
        "ลิงค์": "https://news.thaipbs.or.th/content/318335"
    },
    {
        "วันที่": "2022-08-11 07:00:00",
        "หัวเรื่อง": "ครอบครัวติดใจ รถบัสชนนักศึกษาแพทย์เสียชีวิต จ.ขอนแก่น - ช่อง 7HD",
        "แหล่งข่าว": " ช่อง 7HD",
        "ลิงค์": "https://news.ch7.com/detail/587966"
    },
    {
        "วันที่": "2022-08-11 07:00:00",
        "หัวเรื่อง": "\"มข.-วช.\" มอบชุดตรวจคัดกรองพยาธิใบไม้ตับฯ 4 หมื่นชุดให้กรมควบคุมโรค ถวายเป็นพระราชกุศล \"พระพันปีหลวง\" - สยามรัฐ",
        "แหล่งข่าว": " สยามรัฐ",
        "ลิงค์": "https://siamrath.co.th/n/372864"
    },
    {
        "วันที่": "2022-08-11 07:00:00",
        "หัวเรื่อง": "เผยภาพวงจรปิดนาที รถบัสคณะพยาบาล ทับ นักศึกษาแพทย์ดับคาสามแยกใน มข. - ไทยรัฐ",
        "แหล่งข่าว": " ไทยรัฐ",
        "ลิงค์": "https://www.thairath.co.th/video/news/topnews/hotclip/653527"
    },
    {
        "วันที่": "2022-08-10 07:00:00",
        "หัวเรื่อง": "แห่อาลัย \"น้องอาย\" นักศึกษาแพทย์ปี 2 เสียชีวิตจากอุบัติเหตุรถชน - ไทยรัฐ",
        "แหล่งข่าว": " ไทยรัฐ",
        "ลิงค์": "https://www.thairath.co.th/news/society/2469539"
    },
    {
        "วันที่": "2022-08-10 07:00:00",
        "หัวเรื่อง": "สลด ! นศ. แพทย์ ถูกรถบัสคณะพยาบาลชนดับ 1 เจ็บ 1 กลางสามแยกมหาวิทยาลัย - Kapook.com",
        "แหล่งข่าว": " Kapook.com",
        "ลิงค์": "https://hilight.kapook.com/view/226177"
    },
    {
        "วันที่": "2022-08-10 07:00:00",
        "หัวเรื่อง": "พี่ชายคาใจ จี้ผบห.มหา'ลัยขอนแก่น เหตุรถบัสคณะ ชนน้องสาว นศ.แพทย์ดับ - กรุงเทพธุรกิจ",
        "แหล่งข่าว": " กรุงเทพธุรกิจ",
        "ลิงค์": "https://www.bangkokbiznews.com/social/1020412"
    },
    {
        "วันที่": "2022-08-06 07:00:00",
        "หัวเรื่อง": "มข.เตรียมจัดงาน “งานเกษตรภาคอีสาน ปี 2566” หลังงดจัด 2 ปี เหตุโควิด19 ระบาด - คมชัดลึก",
        "แหล่งข่าว": " คมชัดลึก",
        "ลิงค์": "https://www.komchadluek.net/pr-news/news/525327"
    },
    {
        "วันที่": "2022-08-03 07:00:00",
        "หัวเรื่อง": "ม.ขอนแก่น ผนึกGoogle จัด Hackathon AppSheet พัฒนานวัตกรรมทำงานยุคดิจิทัล - กรุงเทพธุรกิจ",
        "แหล่งข่าว": " กรุงเทพธุรกิจ",
        "ลิงค์": "https://www.bangkokbiznews.com/social/1018919"
    },
    {
        "วันที่": "2022-07-25 07:00:00",
        "หัวเรื่อง": "เปิดวิทยาลัยการคอมพิวเตอร์ ม.ขอนแก่น ผลิตบัณฑิตลุยตลาดงานด้านไซเบอร์ - กรุงเทพธุรกิจ",
        "แหล่งข่าว": " กรุงเทพธุรกิจ",
        "ลิงค์": "https://www.bangkokbiznews.com/social/1017304"
    },
    {
        "วันที่": "2022-07-18 07:00:00",
        "หัวเรื่อง": "ม.ขอนแก่น เปิดวิทยาลัยการคอมพิวเตอร์ มุ่งผลิตคนเก่ง AI ขั้นสูง - ประชาชาติธุรกิจ",
        "แหล่งข่าว": " ประชาชาติธุรกิจ",
        "ลิงค์": "https://www.prachachat.net/education/news-983689"
    },
    {
        "วันที่": "2022-07-06 07:00:00",
        "หัวเรื่อง": "มข. วิจัย “หมอลำ” นำ Soft Power ดัน เศรษฐกิจ สังคม สุขภาพคนอีสาน - กรุงเทพธุรกิจ",
        "แหล่งข่าว": " กรุงเทพธุรกิจ",
        "ลิงค์": "https://www.bangkokbiznews.com/social/1014205"
    },
    {
        "วันที่": "2022-06-29 07:00:00",
        "หัวเรื่อง": "ม.ขอนแก่น ออกประกาศ 9 ข้อ อนุญาตให้นักศึกษาแต่งกายตามเพศสภาพได้ - ประชาชาติธุรกิจ",
        "แหล่งข่าว": " ประชาชาติธุรกิจ",
        "ลิงค์": "https://www.prachachat.net/education/news-966522"
    },
    {
        "วันที่": "2022-06-29 07:00:00",
        "หัวเรื่อง": "ม.ขอนแก่น ต้อนรับนักศึกษาใหม่ หัวใจโด่ดิดง - บ้านเมือง",
        "แหล่งข่าว": " บ้านเมือง",
        "ลิงค์": "https://www.banmuang.co.th/news/education/286030"
    },
    {
        "วันที่": "2022-06-09 07:00:00",
        "หัวเรื่อง": "ทีมวิจัย \"มข.\" พัฒนา KKU-PAPR Suit ป้องกันโควิด ส่งต่อบุคลากรการแพทย์ - กรุงเทพธุรกิจ",
        "แหล่งข่าว": " กรุงเทพธุรกิจ",
        "ลิงค์": "https://www.bangkokbiznews.com/social/1009182"
    },
    {
        "วันที่": "2022-06-07 07:00:00",
        "หัวเรื่อง": "องค์การนักศึกษา ม.ขอนแก่น ประกาศ 'ยกเลิกระบบโซตัส' ทุกรูปแบบ ตั้งแต่ 18 มิ.ย. เป็นต้นไป – THE STANDARD - thestandard.co",
        "แหล่งข่าว": " thestandard.co",
        "ลิงค์": "https://thestandard.co/kku-student-organization-announces-cancel-sotus-system/"
    },
    {
        "วันที่": "2022-06-07 07:00:00",
        "หัวเรื่อง": "ม.ขอนแก่นยกเลิกระบบโซตัสอีกแห่ง ย้ำ \"เวลาเปลี่ยน เราก็ต้องเปลี่ยน\" - ประชาชาติธุรกิจ",
        "แหล่งข่าว": " ประชาชาติธุรกิจ",
        "ลิงค์": "https://www.prachachat.net/education/news-948956"
    },
    {
        "วันที่": "2022-06-06 07:00:00",
        "หัวเรื่อง": "เตรียมตัว! ม.ขอนแก่น รับสมัครสอบ NETSAT เดือน มิ.ย. 65 นี้ (ใช้ยื่น TCAS66-67) - Dek-D.COM",
        "แหล่งข่าว": " Dek-D.COM",
        "ลิงค์": "https://www.dek-d.com/tcas/60299/"
    },
    {
        "วันที่": "2022-06-02 07:00:00",
        "หัวเรื่อง": "สภานักศึกษา ม.ขอนแก่น ยกเลิกใช้คำนำหน้า โอบรับความหลากหลาย - ประชาชาติธุรกิจ",
        "แหล่งข่าว": " ประชาชาติธุรกิจ",
        "ลิงค์": "https://www.prachachat.net/education/news-945986"
    },
    {
        "วันที่": "2022-05-30 07:00:00",
        "หัวเรื่อง": "\"คณะแพทยศาสตร์\" มข. ยกระดับเพิ่มความสะดวก ปชช. เข้าถึงบริการสุขภาพ - กรุงเทพธุรกิจ",
        "แหล่งข่าว": " กรุงเทพธุรกิจ",
        "ลิงค์": "https://www.bangkokbiznews.com/social/1007202"
    },
    {
        "วันที่": "2022-05-27 07:00:00",
        "หัวเรื่อง": "TCAS65 รอบ 4 : มหาวิทยาลัยขอนแก่น (ขยายวันรับ ปิด 3 มิ.ย.นี้ + Update เพิ่มสาขา) - Dek-D.COM",
        "แหล่งข่าว": " Dek-D.COM",
        "ลิงค์": "https://www.dek-d.com/tcas/60426/"
    },
    {
        "วันที่": "2022-05-20 07:00:00",
        "หัวเรื่อง": "#ทีมมข. เตรียมตัว! 26 พ.ค.นี้ ต้องสอบสัมภาษณ์รอบ Admission - Dek-D.COM",
        "แหล่งข่าว": " Dek-D.COM",
        "ลิงค์": "https://www.dek-d.com/tcas/60362/"
    },
    {
        "วันที่": "2022-05-13 07:00:00",
        "หัวเรื่อง": "นิติศาสตร์ มข.ผนึกองค์กรเครือข่ายฯ ประชุมทิศทางการจัดการศึกษาหลักสูตรใหม่ - บ้านเมือง",
        "แหล่งข่าว": " บ้านเมือง",
        "ลิงค์": "https://www.banmuang.co.th/news/region/280485"
    },
    {
        "วันที่": "2022-05-10 07:00:00",
        "หัวเรื่อง": "วิศวะ มข.ผลิตบัณฑิตด้านดิจิทัล เชี่ยวชาญ A.I. เน้น 4 ด้านรองรับภาคอุตสาหกรรม - กรุงเทพธุรกิจ",
        "แหล่งข่าว": " กรุงเทพธุรกิจ",
        "ลิงค์": "https://www.bangkokbiznews.com/social/1003566"
    },
    {
        "วันที่": "2022-05-07 07:00:00",
        "หัวเรื่อง": "ม.ขอนแก่น จัดนิทรรศการโชว์ผลงาน \"วิจัยและนวัตกรรม\" โดดเด่น ปีที่ 2 - กรุงเทพธุรกิจ",
        "แหล่งข่าว": " กรุงเทพธุรกิจ",
        "ลิงค์": "https://www.bangkokbiznews.com/social/1003084"
    },
    {
        "วันที่": "2022-04-26 07:00:00",
        "หัวเรื่อง": "\"มข.\" เปิดตัว Vallaris Maps Platform จัดการข้อมูลด้านภูมิศาสตร์ - กรุงเทพธุรกิจ",
        "แหล่งข่าว": " กรุงเทพธุรกิจ",
        "ลิงค์": "https://www.bangkokbiznews.com/social/1001240"
    },
    {
        "วันที่": "2022-04-19 07:00:00",
        "หัวเรื่อง": "ม.ขอนแก่น เคลียร์ประเด็นสิทธิบัตร \"สเปรย์พ่นปากฟ้าทะลายโจร\" ตกลงเป็นของใคร - กรุงเทพธุรกิจ",
        "แหล่งข่าว": " กรุงเทพธุรกิจ",
        "ลิงค์": "https://www.bangkokbiznews.com/pr-news/biz2u/999953"
    },
    {
        "วันที่": "2022-04-07 07:00:00",
        "หัวเรื่อง": "KKUIC The inspiring entertainment จุดประกายสื่อสร้างสรรค์ - กรุงเทพธุรกิจ",
        "แหล่งข่าว": " กรุงเทพธุรกิจ",
        "ลิงค์": "https://www.bangkokbiznews.com/social/998267"
    },
    {
        "วันที่": "2022-04-06 07:00:00",
        "หัวเรื่อง": "Alibaba เปิดศูนย์นักธุรกิจ 6 หลักสูตร ที่ ม.ขอนแก่น - ประชาชาติธุรกิจ",
        "แหล่งข่าว": " ประชาชาติธุรกิจ",
        "ลิงค์": "https://www.prachachat.net/education/news-904819"
    },
    {
        "วันที่": "2022-04-01 07:00:00",
        "หัวเรื่อง": "มข.มอบปริญญาดุษฎีบัณฑิตกิตติมศักดิ์แด่ “แม่ชีศันสนีย์” - กรุงเทพธุรกิจ",
        "แหล่งข่าว": " กรุงเทพธุรกิจ",
        "ลิงค์": "https://www.bangkokbiznews.com/social/997039"
    },
    {
        "วันที่": "2022-03-29 07:00:00",
        "หัวเรื่อง": "ม.ขอนแก่น ร่วมทุน มิสลิลลี่ ปั้นสตาร์ทอัพไทยโกอินเตอร์ - ผู้จัดการออนไลน์",
        "แหล่งข่าว": " ผู้จัดการออนไลน์",
        "ลิงค์": "https://mgronline.com/business/detail/9650000030641"
    },
    {
        "วันที่": "2022-03-28 07:00:00",
        "หัวเรื่อง": "มข. MOU หัวเว่ย ผลิตบัณฑิต มีทักษะตอบโจทย์อุตสาหกรรมดิจิทัล - กรุงเทพธุรกิจ",
        "แหล่งข่าว": " กรุงเทพธุรกิจ",
        "ลิงค์": "https://www.bangkokbiznews.com/social/996308"
    },
    {
        "วันที่": "2022-03-18 07:00:00",
        "หัวเรื่อง": "How to คิดคะแนน TCAS65 รอบ 2 โควตาภาคฯ มหาวิทยาลัยขอนแก่น - Dek-D.COM",
        "แหล่งข่าว": " Dek-D.COM",
        "ลิงค์": "https://www.dek-d.com/tcas/59942/"
    },
    {
        "วันที่": "2022-03-16 07:00:00",
        "หัวเรื่อง": "สภานักศึกษา มข. ประณาม \"รับน้องโหด\" กรณี \"น้องเปรม\" ถูกรุ่นพี่รุมทำร้ายเสียชีวิต - กรุงเทพธุรกิจ",
        "แหล่งข่าว": " กรุงเทพธุรกิจ",
        "ลิงค์": "https://www.bangkokbiznews.com/news/993936"
    },
    {
        "วันที่": "2022-03-14 07:00:00",
        "หัวเรื่อง": "รีวิว ทุ่งดอกคัตเตอร์ พิกัดลับมหาวิทยาลัยขอนแก่น - TrueID Travel",
        "แหล่งข่าว": " TrueID Travel",
        "ลิงค์": "https://travel.trueid.net/detail/Y3dYKnb9oa1y"
    },
    {
        "วันที่": "2022-03-03 08:00:00",
        "หัวเรื่อง": "มข.เปิด “KKU Smart flower farm 2022” สร้างแนวคิดผู้ประกอบการให้นศ. - กรุงเทพธุรกิจ",
        "แหล่งข่าว": " กรุงเทพธุรกิจ",
        "ลิงค์": "https://www.bangkokbiznews.com/social/991627"
    },
    {
        "วันที่": "2022-02-08 08:00:00",
        "หัวเรื่อง": "นศ.มข.ได้เฮ!หลังออกระเบียบฯใหม่ สามารถเรียน 2-3 เท่าแบบเต็มเวลาและแบบไม่เต็มเวลา - บ้านเมือง",
        "แหล่งข่าว": " บ้านเมือง",
        "ลิงค์": "https://www.banmuang.co.th/news/region/268751"
    },
    {
        "วันที่": "2022-02-07 08:00:00",
        "หัวเรื่อง": "“KKU Production House” หนุนยุคดิจิทัลสำหรับอาจารย์ นศ.มข.ฟรี - กรุงเทพธุรกิจ",
        "แหล่งข่าว": " กรุงเทพธุรกิจ",
        "ลิงค์": "https://www.bangkokbiznews.com/social/987189"
    },
    {
        "วันที่": "2022-02-04 08:00:00",
        "หัวเรื่อง": "สิ้นสุดการรอคอย! เกณฑ์ TCAS65 รอบ 3 Admission มหาวิทยาลัยขอนแก่น - Dek-D.COM",
        "แหล่งข่าว": " Dek-D.COM",
        "ลิงค์": "https://www.dek-d.com/tcas/59490/"
    },
    {
        "วันที่": "2022-01-26 08:00:00",
        "หัวเรื่อง": "วิจัย มข.ติดอันดับมหาวิทยาลัยชั้นนำของโลก - กรุงเทพธุรกิจ",
        "แหล่งข่าว": " กรุงเทพธุรกิจ",
        "ลิงค์": "https://www.bangkokbiznews.com/social/984969"
    },
    {
        "วันที่": "2022-01-09 08:00:00",
        "หัวเรื่อง": "มข.เปิดมาตรการช่วยเหลือนศ.จากผลกระทบโควิด-19 - กรุงเทพธุรกิจ",
        "แหล่งข่าว": " กรุงเทพธุรกิจ",
        "ลิงค์": "https://www.bangkokbiznews.com/social/981764"
    },
    {
        "วันที่": "2021-12-20 01:00:26",
        "หัวเรื่อง": "20 ธันวาคม 2510 - เปิด ม.ขอนแก่น มหาวิทยาลัยแห่งแรกในภาคตะวันออกเฉียงเหนือ – THE STANDARD - thestandard.co",
        "แหล่งข่าว": " เปิด ม.ขอนแก่น มหาวิทยาลัยแห่งแรกในภาคตะวันออกเฉียงเหนือ – THE STANDARD - thestandard.co",
        "ลิงค์": "https://thestandard.co/onthisday20122510/"
    },
    {
        "วันที่": "2021-12-13 08:00:00",
        "หัวเรื่อง": "นศ.ม.ขอนแก่นเหิมหนัก เผาชุดครุยต้านพิธีพระราชทานปริญญาบัตร - ผู้จัดการออนไลน์",
        "แหล่งข่าว": " ผู้จัดการออนไลน์",
        "ลิงค์": "https://mgronline.com/local/detail/9640000123148"
    },
    {
        "วันที่": "2021-11-24 08:00:00",
        "หัวเรื่อง": "TCAS65 รอบ 1 : มหาวิทยาลัยขอนแก่น เริ่ม 1 ธันวาคมนี้ - Dek-D.COM",
        "แหล่งข่าว": " Dek-D.COM",
        "ลิงค์": "https://www.dek-d.com/tcas/59051/"
    }
]